entanglement_enhanced_nlp/__init__.py
entanglement_enhanced_nlp/cli.py
entanglement_enhanced_nlp/licensing.py
entanglement_enhanced_nlp/analysis/__init__.py
entanglement_enhanced_nlp/analysis/correlation_analyzer.py
entanglement_enhanced_nlp/core/__init__.py
entanglement_enhanced_nlp/core/entangled_attention.py
entanglement_enhanced_nlp/core/entangled_embedding.py
entanglement_enhanced_nlp/core/quantum_contextualizer.py
entanglement_enhanced_nlp/transformers/__init__.py
entanglement_enhanced_nlp/transformers/entangled_transformer.py
entanglement_enhanced_nlp/utils/__init__.py
entanglement_enhanced_nlp/utils/quantum_simulator.py
entanglement_enhanced_nlp/visualization/__init__.py
entanglement_enhanced_nlp/visualization/entanglement_visualizer.py
entanglement_enhanced_nlp-2.0.0.dist-info/licenses/LICENSE
entanglement_enhanced_nlp-2.0.0.dist-info/METADATA
entanglement_enhanced_nlp-2.0.0.dist-info/WHEEL
entanglement_enhanced_nlp-2.0.0.dist-info/entry_points.txt
entanglement_enhanced_nlp-2.0.0.dist-info/top_level.txt
entanglement_enhanced_nlp-2.0.0.dist-info/RECORD
