Metadata-Version: 2.4
Name: entanglement-enhanced-nlp
Version: 2.0.0
Summary: Quantum entanglement-inspired Natural Language Processing framework
Home-page: https://github.com/krish567366/entanglement-enhanced-nlp
Author: Krishna Bajpai
Author-email: Krishna Bajpai <bajpaikrishna715@gmail.com>
License: Commercial
Project-URL: Homepage, https://github.com/krish567366/entanglement-enhanced-nlp
Project-URL: Documentation, https://krish567366.github.io/entanglement-enhanced-nlp/
Project-URL: Repository, https://github.com/krish567366/entanglement-enhanced-nlp.git
Project-URL: Bug Tracker, https://github.com/krish567366/entanglement-enhanced-nlp/issues
Keywords: nlp,quantum,entanglement,transformers,embeddings,ai
Classifier: Development Status :: 4 - Beta
Classifier: Intended Audience :: Developers
Classifier: Intended Audience :: Science/Research
Classifier: License :: Other/Proprietary License
Classifier: Operating System :: OS Independent
Classifier: Programming Language :: Python :: 3
Classifier: Programming Language :: Python :: 3.8
Classifier: Programming Language :: Python :: 3.9
Classifier: Programming Language :: Python :: 3.10
Classifier: Programming Language :: Python :: 3.11
Classifier: Programming Language :: Python :: 3.12
Classifier: Topic :: Scientific/Engineering :: Artificial Intelligence
Classifier: Topic :: Scientific/Engineering :: Physics
Classifier: Topic :: Text Processing :: Linguistic
Requires-Python: >=3.8
License-File: LICENSE
Requires-Dist: torch>=1.9.0
Requires-Dist: transformers>=4.20.0
Requires-Dist: numpy>=1.21.0
Requires-Dist: scipy>=1.7.0
Requires-Dist: pandas>=1.3.0
Requires-Dist: matplotlib>=3.4.0
Requires-Dist: seaborn>=0.11.0
Requires-Dist: networkx>=2.6.0
Requires-Dist: plotly>=5.0.0
Requires-Dist: click>=8.0.0
Requires-Dist: tqdm>=4.62.0
Requires-Dist: pyyaml>=6.0
Requires-Dist: scikit-learn>=1.0.0
Requires-Dist: pennylane>=0.28.0
Requires-Dist: quantummeta-license>=1.0.0
Provides-Extra: dev
Requires-Dist: pytest>=6.0; extra == "dev"
Requires-Dist: pytest-cov>=2.12.0; extra == "dev"
Requires-Dist: black>=21.0.0; extra == "dev"
Requires-Dist: flake8>=3.9.0; extra == "dev"
Requires-Dist: mypy>=0.910; extra == "dev"
Requires-Dist: pre-commit>=2.15.0; extra == "dev"
Requires-Dist: jupyter>=1.0.0; extra == "dev"
Requires-Dist: ipykernel>=6.0.0; extra == "dev"
Requires-Dist: nbconvert>=6.0.0; extra == "dev"
Provides-Extra: docs
Requires-Dist: sphinx>=4.0.0; extra == "docs"
Requires-Dist: sphinx-rtd-theme>=1.0.0; extra == "docs"
Requires-Dist: sphinx-autodoc-typehints>=1.12.0; extra == "docs"
Dynamic: author
Dynamic: home-page
Dynamic: license-file
Dynamic: requires-python
